{
  "feature_graph": {
    "order": [
      "feature:sketch_base",
      "feature:extrude_base",
      "feature:sketch_boss",
      "feature:boss_join"
    ],
    "features": {
      "feature:sketch_base": {
        "id": "feature:sketch_base",
        "name": "Base Sketch",
        "feature_type": "sketch",
        "suppressed": false,
        "dirty": false
      },
      "feature:extrude_base": {
        "id": "feature:extrude_base",
        "name": "Extrude Base",
        "feature_type": "extrude",
        "suppressed": false,
        "dirty": false
      },
      "feature:sketch_boss": {
        "id": "feature:sketch_boss",
        "name": "Boss Sketch",
        "feature_type": "sketch",
        "suppressed": false,
        "dirty": false
      },
      "feature:boss_join": {
        "id": "feature:boss_join",
        "name": "Boss Join",
        "feature_type": "extrude",
        "suppressed": false,
        "dirty": false
      }
    },
    "edges": [
      {
        "source": "feature:sketch_base",
        "target": "feature:extrude_base",
        "kind": "depends_on"
      },
      {
        "source": "feature:sketch_boss",
        "target": "feature:boss_join",
        "kind": "depends_on"
      },
      {
        "source": "feature:extrude_base",
        "target": "feature:boss_join",
        "kind": "depends_on"
      }
    ]
  },
  "feature_nodes": [
    {
      "id": "feature:boss_join",
      "name": "Boss Join",
      "definition": {
        "type": "extrude",
        "sketch_feature": "feature:sketch_boss",
        "profile_ref": "sketch:boss/profile:outer",
        "extent": {
          "type": "distance",
          "length": {
            "value_si": 0.012
          }
        },
        "operation": "join",
        "length_expr": "thickness * 2",
        "target_feature": "feature:extrude_base"
      },
      "suppressed": false
    },
    {
      "id": "feature:extrude_base",
      "name": "Extrude Base",
      "definition": {
        "type": "extrude",
        "sketch_feature": "feature:sketch_base",
        "profile_ref": "sketch:base/profile:outer",
        "extent": {
          "type": "distance",
          "length": {
            "value_si": 0.006
          }
        },
        "operation": "new_body",
        "length_expr": "thickness"
      },
      "suppressed": false
    },
    {
      "id": "feature:sketch_base",
      "name": "Base Sketch",
      "definition": {
        "type": "sketch",
        "sketch_id": "sketch:base"
      },
      "suppressed": false
    },
    {
      "id": "feature:sketch_boss",
      "name": "Boss Sketch",
      "definition": {
        "type": "sketch",
        "sketch_id": "sketch:boss"
      },
      "suppressed": false
    }
  ]
}
